{
  "updated": "2026-05-06T02:07:34.253532Z",
  "upcoming": [
    {
      "type": "Bill",
      "term": "17-Week",
      "auctionDate": "2026-05-06",
      "issueDate": "2026-05-12",
      "offeringAmt": 69000000000.0,
      "cusip": "912797VB0"
    },
    {
      "type": "Bill",
      "term": "4-Week",
      "auctionDate": "2026-05-07",
      "issueDate": "2026-05-12",
      "offeringAmt": 90000000000.0,
      "cusip": "912797TZ0"
    },
    {
      "type": "Bill",
      "term": "8-Week",
      "auctionDate": "2026-05-07",
      "issueDate": "2026-05-12",
      "offeringAmt": 85000000000.0,
      "cusip": "912797UN5"
    },
    {
      "type": "Bill",
      "term": "13-Week",
      "auctionDate": "2026-05-11",
      "issueDate": "2026-05-14",
      "offeringAmt": 0.0,
      "cusip": "912797TW7"
    },
    {
      "type": "Bill",
      "term": "26-Week",
      "auctionDate": "2026-05-11",
      "issueDate": "2026-05-14",
      "offeringAmt": 0.0,
      "cusip": "912797UY1"
    },
    {
      "type": "Bill",
      "term": "52-Week",
      "auctionDate": "2026-05-12",
      "issueDate": "2026-05-14",
      "offeringAmt": 0.0,
      "cusip": "912797UX3"
    },
    {
      "type": "Bill",
      "term": "6-Week",
      "auctionDate": "2026-05-12",
      "issueDate": "2026-05-14",
      "offeringAmt": 0.0,
      "cusip": "912797TE7"
    },
    {
      "type": "Note",
      "term": "3-Year",
      "auctionDate": "2026-05-11",
      "issueDate": "2026-05-15",
      "offeringAmt": 0.0,
      "cusip": "91282CQR5"
    },
    {
      "type": "Note",
      "term": "10-Year",
      "auctionDate": "2026-05-12",
      "issueDate": "2026-05-15",
      "offeringAmt": 0.0,
      "cusip": "91282CQQ7"
    },
    {
      "type": "Bond",
      "term": "30-Year",
      "auctionDate": "2026-05-13",
      "issueDate": "2026-05-15",
      "offeringAmt": 0.0,
      "cusip": "912810UU0"
    }
  ],
  "auctioned": [
    {
      "type": "Bill",
      "term": "6-Week",
      "auctionDate": "2026-05-05",
      "issueDate": "2026-05-07",
      "offeringAmt": 75000000000.0,
      "cusip": "912797TD9",
      "highRate": ""
    },
    {
      "type": "Bill",
      "term": "13-Week",
      "auctionDate": "2026-05-04",
      "issueDate": "2026-05-07",
      "offeringAmt": 89000000000.0,
      "cusip": "912797RG4",
      "highRate": ""
    },
    {
      "type": "Bill",
      "term": "26-Week",
      "auctionDate": "2026-05-04",
      "issueDate": "2026-05-07",
      "offeringAmt": 77000000000.0,
      "cusip": "912797UM7",
      "highRate": ""
    },
    {
      "type": "Bill",
      "term": "4-Week",
      "auctionDate": "2026-04-30",
      "issueDate": "2026-05-05",
      "offeringAmt": 80000000000.0,
      "cusip": "912797TU1",
      "highRate": ""
    },
    {
      "type": "Bill",
      "term": "8-Week",
      "auctionDate": "2026-04-30",
      "issueDate": "2026-05-05",
      "offeringAmt": 75000000000.0,
      "cusip": "912797UC9",
      "highRate": ""
    },
    {
      "type": "Bill",
      "term": "17-Week",
      "auctionDate": "2026-04-29",
      "issueDate": "2026-05-05",
      "offeringAmt": 69000000000.0,
      "cusip": "912797UW5",
      "highRate": ""
    },
    {
      "type": "Note",
      "term": "7-Year",
      "auctionDate": "2026-04-28",
      "issueDate": "2026-04-30",
      "offeringAmt": 44000000000.0,
      "cusip": "91282CQN4",
      "highRate": "4.1750"
    },
    {
      "type": "Note",
      "term": "2-Year",
      "auctionDate": "2026-04-27",
      "issueDate": "2026-04-30",
      "offeringAmt": 69000000000.0,
      "cusip": "91282CQL8",
      "highRate": "3.8120"
    },
    {
      "type": "Note",
      "term": "5-Year",
      "auctionDate": "2026-04-27",
      "issueDate": "2026-04-30",
      "offeringAmt": 70000000000.0,
      "cusip": "91282CQK0",
      "highRate": "3.9550"
    },
    {
      "type": "Bond",
      "term": "19-Year 10-Month",
      "auctionDate": "2026-04-22",
      "issueDate": "2026-04-30",
      "offeringAmt": 13000000000.0,
      "cusip": "912810UT3",
      "highRate": "4.8830"
    },
    {
      "type": "Bill",
      "term": "52-Week",
      "auctionDate": "2026-04-14",
      "issueDate": "2026-04-16",
      "offeringAmt": 50000000000.0,
      "cusip": "912797UE5",
      "highRate": ""
    },
    {
      "type": "Bond",
      "term": "29-Year 10-Month",
      "auctionDate": "2026-04-09",
      "issueDate": "2026-04-15",
      "offeringAmt": 22000000000.0,
      "cusip": "912810UR7",
      "highRate": "4.8760"
    },
    {
      "type": "Note",
      "term": "9-Year 10-Month",
      "auctionDate": "2026-04-08",
      "issueDate": "2026-04-15",
      "offeringAmt": 39000000000.0,
      "cusip": "91282CPZ8",
      "highRate": "4.2820"
    },
    {
      "type": "Note",
      "term": "3-Year",
      "auctionDate": "2026-04-07",
      "issueDate": "2026-04-15",
      "offeringAmt": 58000000000.0,
      "cusip": "91282CQJ3",
      "highRate": "3.8970"
    }
  ]
}